pipelined_processor.v
`timescale 1ns/1ps

module pipelined_processor (
    input wire clk,
    input wire reset
);

    // =========================================================
    // OPCODES
    // =========================================================
    localparam OP_ADD  = 2'b00;
    localparam OP_SUB  = 2'b01;
    localparam OP_LOAD = 2'b10;

    // =========================================================
    // PROGRAM COUNTER
    // =========================================================
    reg [3:0] pc;

    // =========================================================
    // REGISTER FILE
    // 8 registers, each 8 bits wide
    // =========================================================
    reg [7:0] registers [0:7];

    // =========================================================
    // DATA MEMORY
    // 16 locations, each 8 bits
    // =========================================================
    reg [7:0] data_memory [0:15];

    // =========================================================
    // INSTRUCTION MEMORY
    //
    // Instruction format:
    // [15:14] = opcode
    // [13:11] = destination register
    // [10:8]  = source register 1
    // [7:5]   = source register 2
    // [4:0]   = immediate
    // =========================================================
    reg [15:0] instruction_memory [0:15];

    // =========================================================
    // STAGE 1: IF - INSTRUCTION FETCH
    // =========================================================
    reg [15:0] if_instruction;
    reg [3:0]  if_pc;

    // =========================================================
    // STAGE 2: ID - INSTRUCTION DECODE
    // =========================================================
    reg [1:0]  id_opcode;
    reg [2:0]  id_rd;
    reg [2:0]  id_rs1;
    reg [2:0]  id_rs2;
    reg [4:0]  id_imm;

    reg [7:0]  id_data1;
    reg [7:0]  id_data2;

    // =========================================================
    // STAGE 3: EX - EXECUTE
    // =========================================================
    reg [1:0]  ex_opcode;
    reg [2:0]  ex_rd;
    reg [7:0]  ex_result;

    // =========================================================
    // STAGE 4: WB - WRITE BACK
    // =========================================================
    reg [2:0] wb_rd;
    reg [7:0] wb_result;
    reg        wb_valid;

    integer i;

    // =========================================================
    // INITIALIZE MEMORIES
    // =========================================================
    initial begin

        // Initialize registers
        for (i = 0; i < 8; i = i + 1)
            registers[i] = 8'd0;

        // Initialize data memory
        for (i = 0; i < 16; i = i + 1)
            data_memory[i] = 8'd0;

        // Initialize instruction memory
        for (i = 0; i < 16; i = i + 1)
            instruction_memory[i] = 16'd0;

        // -----------------------------------------------------
        // Initial register values
        // -----------------------------------------------------
        registers[2] = 8'd10;
        registers[3] = 8'd20;

        registers[5] = 8'd30;
        registers[6] = 8'd10;

        registers[7] = 8'd4;

        // -----------------------------------------------------
        // Data memory
        // -----------------------------------------------------
        data_memory[4] = 8'd100;

        // -----------------------------------------------------
        // Instructions
        //
        // ADD R1,R2,R3
        // R1 = R2 + R3 = 10 + 20 = 30
        //
        // SUB R4,R5,R6
        // R4 = R5 - R6 = 30 - 10 = 20
        //
        // LOAD R0,0(R7)
        // R0 = Memory[R7 + 0]
        // R7 = 4
        // Memory[4] = 100
        // -----------------------------------------------------

        instruction_memory[0] =
            {OP_ADD, 3'd1, 3'd2, 3'd3, 5'd0};

        instruction_memory[1] =
            {OP_SUB, 3'd4, 3'd5, 3'd6, 5'd0};

        instruction_memory[2] =
            {OP_LOAD, 3'd0, 3'd7, 3'd0, 5'd0};

    end

    // =========================================================
    // PIPELINE
    // =========================================================
    always @(posedge clk) begin

        if (reset) begin

            pc = 4'd0;

            if_instruction = 16'd0;
            if_pc = 4'd0;

            id_opcode = 2'd0;
            id_rd = 3'd0;
            id_rs1 = 3'd0;
            id_rs2 = 3'd0;
            id_imm = 5'd0;

            id_data1 = 8'd0;
            id_data2 = 8'd0;

            ex_opcode = 2'd0;
            ex_rd = 3'd0;
            ex_result = 8'd0;

            wb_rd = 3'd0;
            wb_result = 8'd0;
            wb_valid = 1'b0;

        end

        else begin

            // =================================================
            // STAGE 4: WRITE BACK
            // =================================================
            if (wb_valid) begin
                registers[wb_rd] <= wb_result;
            end

            wb_rd <= ex_rd;
            wb_result <= ex_result;
            wb_valid <= 1'b1;


            // =================================================
            // STAGE 3: EXECUTE
            // =================================================
            ex_opcode <= id_opcode;
            ex_rd <= id_rd;

            case (id_opcode)

                OP_ADD: begin
                    ex_result <= id_data1 + id_data2;
                end

                OP_SUB: begin
                    ex_result <= id_data1 - id_data2;
                end

                OP_LOAD: begin
                    ex_result <= data_memory[id_data1 + id_imm];
                end

                default: begin
                    ex_result <= 8'd0;
                end

            endcase


            // =================================================
            // STAGE 2: INSTRUCTION DECODE
            // =================================================
            id_opcode <= if_instruction[15:14];
            id_rd     <= if_instruction[13:11];
            id_rs1    <= if_instruction[10:8];
            id_rs2    <= if_instruction[7:5];
            id_imm    <= if_instruction[4:0];

            id_data1 <= registers[if_instruction[10:8]];
            id_data2 <= registers[if_instruction[7:5]];


            // =================================================
            // STAGE 1: INSTRUCTION FETCH
            // =================================================
            if_instruction <= instruction_memory[pc];
            if_pc <= pc;

            pc <= pc + 1'b1;

        end

    end

endmodule

tb_pipelined_processor.v
`timescale 1ns/1ps

module tb_pipelined_processor;

    reg clk;
    reg reset;

    // Instantiate processor
    pipelined_processor uut (
        .clk(clk),
        .reset(reset)
    );

    // Clock generation
    always #5 clk = ~clk;

    initial begin  
        $dumpfile("processor.vcd");
$dumpvars(0, tb_pipelined_processor);

        // Initial values
        clk = 0;
        reset = 1;

        // Reset processor
        #10;
        reset = 0;

        // Allow pipeline to execute
        #100;

        // Display final register values
        $display("====================================");
        $display("      PIPELINED PROCESSOR RESULT     ");
        $display("====================================");

        $display("R0 = %d", uut.registers[0]);
        $display("R1 = %d", uut.registers[1]);
        $display("R4 = %d", uut.registers[4]);

        $display("====================================");

        $finish;

    end

endmodule

processor.vcd
$date
	Sun Sep 06 13:11:46 2026
$end
$version
	Icarus Verilog
$end
$timescale
	1ps
$end
$scope module tb_pipelined_processor $end
$var reg 1 ! clk $end
$var reg 1 " reset $end
$scope module uut $end
$var wire 1 ! clk $end
$var wire 1 " reset $end
$var reg 2 # ex_opcode [1:0] $end
$var reg 3 $ ex_rd [2:0] $end
$var reg 8 % ex_result [7:0] $end
$var reg 8 & id_data1 [7:0] $end
$var reg 8 ' id_data2 [7:0] $end
$var reg 5 ( id_imm [4:0] $end
$var reg 2 ) id_opcode [1:0] $end
$var reg 3 * id_rd [2:0] $end
$var reg 3 + id_rs1 [2:0] $end
$var reg 3 , id_rs2 [2:0] $end
$var reg 16 - if_instruction [15:0] $end
$var reg 4 . if_pc [3:0] $end
$var reg 4 / pc [3:0] $end
$var reg 3 0 wb_rd [2:0] $end
$var reg 8 1 wb_result [7:0] $end
$var reg 1 2 wb_valid $end
$var integer 32 3 i [31:0] $end
$upscope $end
$upscope $end
$enddefinitions $end
#0
$dumpvars
b10000 3
x2
bx 1
bx 0
bx /
bx .
bx -
bx ,
bx +
bx *
bx )
bx (
bx '
bx &
bx %
bx $
bx #
1"
0!
$end
#5000
02
b0 1
b0 0
b0 %
b0 $
b0 #
b0 '
b0 &
b0 (
b0 ,
b0 +
b0 *
b0 )
b0 .
b0 -
b0 /
1!
#10000
0!
0"
#15000
b1 /
b101001100000 -
12
1!
#20000
0!
#25000
b10 /
b1 .
b110010111000000 -
b10100 '
b1010 &
b11 ,
b10 +
b1 *
1!
#30000
0!
#35000
b11 /
b10 .
b1000011100000000 -
b1010 '
b11110 &
b110 ,
b101 +
b100 *
b1 )
b11110 %
b1 $
1!
#40000
0!
#45000
b100 /
b11 .
b0 -
b0 '
b100 &
b0 ,
b111 +
b0 *
b10 )
b10100 %
b100 $
b1 #
b11110 1
b1 0
1!
#50000
0!
#55000
b101 /
b100 .
b0 &
b0 +
b0 )
b1100100 %
b0 $
b10 #
b10100 1
b100 0
1!
#60000
0!
#65000
b110 /
b101 .
b0 %
b0 #
b1100100 1
b0 0
1!
#70000
0!
#75000
b111 /
b110 .
b0 1
1!
#80000
0!
#85000
b1000 /
b111 .
b1100100 '
b1100100 &
1!
#90000
0!
#95000
b1001 /
b1000 .
b0 '
b0 &
b11001000 %
1!
#100000
0!
#105000
b1010 /
b1001 .
b0 %
b11001000 1
1!
